[
  {
    "idUser": "5f4e8b5d96a75f14a8d7001a",
    "source": {
      "city": "City1",
      "street": "Street1",
      "houseNumber": "123"
    },
    "destination": {
      "city": "City2",
      "street": "Street2",
      "houseNumber": "456"
    },
    "limitDate": "2023-01-15T12:00:00Z"
  },
  {
    "idUser": "5f4e8b5d96a75f14a8d7001b",
    "source": {
      "city": "City3",
      "street": "Street3",
      "houseNumber": "789"
    },
    "destination": {
      "city": "City4",
      "street": "Street4",
      "houseNumber": "101"
    },
    "limitDate": "2023-02-28T18:30:00Z"
  },
  {
    "idUser": null,
    "source": {
      "city": "City5",
      "street": "Street5",
      "houseNumber": "222"
    },
    "destination": {
      "city": "City6",
      "street": "Street6",
      "houseNumber": "333"
    },
    "limitDate": "2023-03-10T08:45:00Z"
  }
]
